odoo/addons/shopinvader_product_template_multi_link_date_span/README.rst
odoo/addons/shopinvader_product_template_multi_link_date_span/__init__.py
odoo/addons/shopinvader_product_template_multi_link_date_span/__manifest__.py
odoo/addons/shopinvader_product_template_multi_link_date_span/i18n/shopinvader_product_template_multi_link_date_span.pot
odoo/addons/shopinvader_product_template_multi_link_date_span/models/__init__.py
odoo/addons/shopinvader_product_template_multi_link_date_span/models/shopinvader_product_link_mixin.py
odoo/addons/shopinvader_product_template_multi_link_date_span/readme/CONTRIBUTORS.rst
odoo/addons/shopinvader_product_template_multi_link_date_span/readme/CREDITS.rst
odoo/addons/shopinvader_product_template_multi_link_date_span/readme/DESCRIPTION.rst
odoo/addons/shopinvader_product_template_multi_link_date_span/static/description/index.html
odoo/addons/shopinvader_product_template_multi_link_date_span/tests/__init__.py
odoo/addons/shopinvader_product_template_multi_link_date_span/tests/test_product.py
odoo14_addon_shopinvader_product_template_multi_link_date_span-14.0.1.0.1.dev3.dist-info/METADATA
odoo14_addon_shopinvader_product_template_multi_link_date_span-14.0.1.0.1.dev3.dist-info/WHEEL
odoo14_addon_shopinvader_product_template_multi_link_date_span-14.0.1.0.1.dev3.dist-info/top_level.txt
odoo14_addon_shopinvader_product_template_multi_link_date_span-14.0.1.0.1.dev3.dist-info/RECORD
